robosuite/__init__.py
robosuite/macros.py
robosuite/controllers/__init__.py
robosuite/controllers/composite/__init__.py
robosuite/controllers/composite/composite_controller.py
robosuite/controllers/composite/composite_controller_factory.py
robosuite/controllers/config/default/composite/basic.json
robosuite/controllers/config/default/composite/hybrid_mobile_base.json
robosuite/controllers/config/default/composite/whole_body_ik.json
robosuite/controllers/config/default/composite/whole_body_mink_ik.json
robosuite/controllers/config/default/parts/ik_pose.json
robosuite/controllers/config/default/parts/joint_position.json
robosuite/controllers/config/default/parts/joint_torque.json
robosuite/controllers/config/default/parts/joint_velocity.json
robosuite/controllers/config/default/parts/osc_pose.json
robosuite/controllers/config/default/parts/osc_position.json
robosuite/controllers/config/robots/default_baxter.json
robosuite/controllers/config/robots/default_gr1.json
robosuite/controllers/config/robots/default_gr1_fixed_lower_body.json
robosuite/controllers/config/robots/default_gr1_floating_body.json
robosuite/controllers/config/robots/default_iiwa.json
robosuite/controllers/config/robots/default_kinova3.json
robosuite/controllers/config/robots/default_panda.json
robosuite/controllers/config/robots/default_panda_dex.json
robosuite/controllers/config/robots/default_pandaomron.json
robosuite/controllers/config/robots/default_pandaomron_whole_body_ik.json
robosuite/controllers/config/robots/default_sawyer.json
robosuite/controllers/config/robots/default_spotwitharm.json
robosuite/controllers/config/robots/default_tiago.json
robosuite/controllers/config/robots/default_tiago_whole_body_ik.json
robosuite/controllers/config/robots/default_ur5e.json
robosuite/controllers/parts/__init__.py
robosuite/controllers/parts/controller.py
robosuite/controllers/parts/controller_factory.py
robosuite/controllers/parts/arm/__init__.py
robosuite/controllers/parts/arm/ik.py
robosuite-1.5.2.dist-info/licenses/AUTHORS
robosuite-1.5.2.dist-info/licenses/LICENSE
robosuite-1.5.2.dist-info/METADATA
robosuite-1.5.2.dist-info/WHEEL
robosuite-1.5.2.dist-info/eager_resources.txt
robosuite-1.5.2.dist-info/top_level.txt
robosuite-1.5.2.dist-info/RECORD
