Metadata-Version: 2.4
Name: robosuite
Version: 1.5.2
Summary: robosuite: A Modular Simulation Framework and Benchmark for Robot Learning
Home-page: https://github.com/ARISE-Initiative/robosuite
Author: Yuke Zhu
Author-email: yukez@cs.utexas.edu
Requires-Python: >=3
License-File: LICENSE
License-File: AUTHORS
Requires-Dist: numpy>=1.13.3
Requires-Dist: numba>=0.49.1
Requires-Dist: scipy>=1.2.3
Requires-Dist: mujoco>=3.3.0
Requires-Dist: mink==0.0.5
Requires-Dist: qpsolvers[quadprog]>=4.3.1
Requires-Dist: Pillow
Requires-Dist: opencv-python
Requires-Dist: pynput
Requires-Dist: termcolor
Requires-Dist: pytest
Requires-Dist: tqdm
Dynamic: author
Dynamic: author-email
Dynamic: description
Dynamic: description-content-type
Dynamic: home-page
Dynamic: license-file
Dynamic: requires-dist
Dynamic: requires-python
Dynamic: summary
